{
  "id": "features/type-checking",
  "title": "Type Checking",
  "description": "Detect type mismatches between how variables are used and their actual values.",
  "source": "@site/docs/features/type-checking.md",
  "sourceDirName": "features",
  "slug": "/features/type-checking",
  "permalink": "/env-doctor/docs/features/type-checking",
  "draft": false,
  "unlisted": false,
  "editUrl": "https://github.com/khushwantparihar/env-doctor/tree/main/docs/docs/features/type-checking.md",
  "tags": [],
  "version": "current",
  "sidebarPosition": 3,
  "frontMatter": {
    "sidebar_position": 3
  },
  "sidebar": "docsSidebar",
  "previous": {
    "title": "Unused Variable Detection",
    "permalink": "/env-doctor/docs/features/unused-vars"
  },
  "next": {
    "title": "Secret Detection",
    "permalink": "/env-doctor/docs/features/secret-detection"
  }
}